wacc/__init__.py
wacc-0.0.1.dist-info/LICENSE
wacc-0.0.1.dist-info/METADATA
wacc-0.0.1.dist-info/WHEEL
wacc-0.0.1.dist-info/top_level.txt
wacc-0.0.1.dist-info/RECORD
