Metadata-Version: 2.1
Name: wacc
Version: 0.0.1
Summary: The Python micro framework for deriving cost of capital
Home-page: https://github.com/pax1a/wacc
Author: pax1a
Author-email: author@example.com
License: UNKNOWN
Platform: UNKNOWN
Classifier: Programming Language :: Python :: 3
Classifier: License :: OSI Approved :: BSD License
Classifier: Operating System :: OS Independent
Requires-Python: >=3.6
